{"backgroundLayers":[{"backgroundRows":[{},{"items":["NO_SPRITE","NO_SPRITE","NO_SPRITE","NO_SPRITE","GRASS","GRASS","GRASS","GRASS","GRASS","GRASS","GRASS","GRASS","GRASS","DIRT_ROAD_INNER_TOP_LEFT_CORNER","DIRT_ROAD_INNER_TOP_RIGHT_CORNER","GRASS","GRASS","GRASS","GRASS","GRASS","GRASS","GRASS","GRASS","GRASS","GRASS","GRASS","GRASS","GRASS","GRASS","GRASS","GRASS","GRASS","GRASS","GRASS","GRASS","GRASS","GRASS","GRASS","GRASS","GRASS","GRASS","GRASS","GRASS"]},{"items":["NO_SPRITE","NO_SPRITE","NO_SPRITE","NO_SPRITE","DIRT_ROAD_CORRIDOR_HORIZONTAL","DIRT_ROAD_CORRIDOR_HORIZONTAL","DIRT_ROAD_CORRIDOR_HORIZONTAL","DIRT_ROAD_CORRIDOR_HORIZONTAL","DIRT_ROAD_CORRIDOR_HORIZONTAL","DIRT_ROAD_CORRIDOR_HORIZONTAL","DIRT_ROAD_CORRIDOR_HORIZONTAL","DIRT_ROAD_CORRIDOR_HORIZONTAL","GRASS","DIRT_ROAD_INNER_BOTTOM_LEFT_CORNER","DIRT_ROAD_INNER_BOTTOM_RIGHT_CORNER","GRASS","DIRT_ROAD_CORRIDOR_HORIZONTAL","DIRT_ROAD_CORRIDOR_HORIZONTAL","DIRT_ROAD_CORRIDOR_HORIZONTAL","DIRT_ROAD_CORRIDOR_HORIZONTAL","DIRT_ROAD_CORRIDOR_HORIZONTAL","DIRT_ROAD_CORRIDOR_HORIZONTAL","DIRT_ROAD_CORRIDOR_HORIZONTAL","DIRT_ROAD_CORRIDOR_HORIZONTAL","DIRT_ROAD_INNER_TOP_LEFT_CORNER","DIRT_ROAD_INNER_TOP_RIGHT_CORNER","DIRT_ROAD_INNER_TOP_LEFT_CORNER","DIRT_ROAD_INNER_TOP_RIGHT_CORNER","GRASS","GRASS","GRASS","GRASS","GRASS","GRASS","GRASS","GRASS","DIRT_ROAD_INNER_TOP_LEFT_CORNER","DIRT_ROAD_INNER_TOP_RIGHT_CORNER","DIRT_ROAD_INNER_TOP_LEFT_CORNER","DIRT_ROAD_INNER_TOP_RIGHT_CORNER","DIRT_ROAD_INNER_TOP_LEFT_CORNER","DIRT_ROAD_INNER_TOP_RIGHT_CORNER","GRASS"]},{"items":["NO_SPRITE","NO_SPRITE","NO_SPRITE","NO_SPRITE","DARK_PATH_CORRIDOR_HORIZONTAL","DARK_PATH_CORRIDOR_HORIZONTAL","DARK_PATH_CORRIDOR_HORIZONTAL","DARK_PATH_CORRIDOR_HORIZONTAL","DARK_PATH_CORRIDOR_HORIZONTAL","DARK_PATH_CORRIDOR_HORIZONTAL","DARK_PATH_CORRIDOR_HORIZONTAL","DARK_PATH_CORRIDOR_HORIZONTAL","DIRT_ROAD_INNER_TOP_LEFT_CORNER","DIRT_ROAD_INNER_TOP_RIGHT_CORNER","DIRT_ROAD_INNER_TOP_LEFT_CORNER","DIRT_ROAD_INNER_TOP_RIGHT_CORNER","DARK_PATH_CORRIDOR_HORIZONTAL","DARK_PATH_CORRIDOR_HORIZONTAL","DARK_PATH_CORRIDOR_HORIZONTAL","DARK_PATH_CORRIDOR_HORIZONTAL","DARK_PATH_CORRIDOR_HORIZONTAL","DARK_PATH_CORRIDOR_HORIZONTAL","DARK_PATH_CORRIDOR_HORIZONTAL","DARK_PATH_CORRIDOR_HORIZONTAL","DIRT_ROAD_INNER_BOTTOM_LEFT_CORNER","DIRT_ROAD_INNER_BOTTOM_RIGHT_CORNER","DIRT_ROAD_INNER_BOTTOM_LEFT_CORNER","DIRT_ROAD_INNER_BOTTOM_RIGHT_CORNER","DARK_PATH_CORRIDOR_HORIZONTAL","DARK_PATH_CORRIDOR_HORIZONTAL","DARK_PATH_CORRIDOR_HORIZONTAL","DARK_PATH_CORRIDOR_HORIZONTAL","DARK_PATH_CORRIDOR_HORIZONTAL","DARK_PATH_CORRIDOR_HORIZONTAL","DARK_PATH_CORRIDOR_HORIZONTAL","DARK_PATH_CORRIDOR_HORIZONTAL","DIRT_ROAD_INNER_BOTTOM_LEFT_CORNER","DIRT_ROAD_INNER_BOTTOM_RIGHT_CORNER","DIRT_ROAD_INNER_BOTTOM_LEFT_CORNER","DIRT_ROAD_INNER_BOTTOM_RIGHT_CORNER","DIRT_ROAD_INNER_BOTTOM_LEFT_CORNER","DIRT_ROAD_INNER_BOTTOM_RIGHT_CORNER","GRASS"]},{"items":["NO_SPRITE","NO_SPRITE","NO_SPRITE","NO_SPRITE","GRASS","GRASS","GRASS","GRASS","GRASS","GRASS","GRASS","GRASS","DIRT_ROAD_INNER_BOTTOM_LEFT_CORNER","DIRT_ROAD_INNER_BOTTOM_RIGHT_CORNER","DIRT_ROAD_INNER_BOTTOM_LEFT_CORNER","DIRT_ROAD_INNER_BOTTOM_RIGHT_CORNER","GRASS","GRASS","GRASS","GRASS","GRASS","GRASS","GRASS","GRASS","GRASS","GRASS","GRASS","GRASS","GRASS","GRASS","GRASS","GRASS","GRASS","GRASS","GRASS","GRASS","GRASS","GRASS","GRASS","GRASS","GRASS","GRASS","GRASS"]},{"items":["NO_SPRITE","NO_SPRITE","NO_SPRITE","NO_SPRITE","NO_SPRITE","NO_SPRITE","NO_SPRITE","NO_SPRITE","NO_SPRITE","NO_SPRITE","NO_SPRITE","NO_SPRITE","GRASS","DIRT_ROAD_CORRIDOR_VERTICAL","DARK_PATH_CORRIDOR_VERTICAL","GRASS","GRASS","GRASS","GRASS","GRASS","GRASS","GRASS","GRASS","GRASS","GRASS","GRASS","GRASS","GRASS","GRASS","GRASS","GRASS","GRASS","GRASS","GRASS","GRASS","GRASS","GRASS","DIRT_ROAD_CORRIDOR_VERTICAL","DARK_PATH_CORRIDOR_VERTICAL","GRASS","GRASS","GRASS","GRASS"]},{"items":["NO_SPRITE","NO_SPRITE","NO_SPRITE","NO_SPRITE","NO_SPRITE","NO_SPRITE","NO_SPRITE","NO_SPRITE","NO_SPRITE","NO_SPRITE","NO_SPRITE","NO_SPRITE","GRASS","DIRT_ROAD_CORRIDOR_VERTICAL","DARK_PATH_CORRIDOR_VERTICAL","GRASS","GRASS","GRASS","GRASS","GRASS","GRASS","GRASS","GRASS","GRASS","GRASS","GRASS","GRASS","GRASS","GRASS","GRASS","GRASS","GRASS","GRASS","GRASS","GRASS","GRASS","GRASS","DIRT_ROAD_CORRIDOR_VERTICAL","DARK_PATH_CORRIDOR_VERTICAL","GRASS","GRASS","GRASS","GRASS"]},{"items":["NO_SPRITE","NO_SPRITE","NO_SPRITE","NO_SPRITE","NO_SPRITE","NO_SPRITE","NO_SPRITE","NO_SPRITE","NO_SPRITE","NO_SPRITE","NO_SPRITE","NO_SPRITE","GRASS","DIRT_ROAD_CORRIDOR_VERTICAL","DARK_PATH_CORRIDOR_VERTICAL","GRASS","GRASS","GRASS","GRASS","GRASS","GRASS","GRASS","GRASS","GRASS","GRASS","GRASS","GRASS","GRASS","GRASS","GRASS","GRASS","GRASS","GRASS","GRASS","GRASS","GRASS","GRASS","DIRT_ROAD_CORRIDOR_VERTICAL","DARK_PATH_CORRIDOR_VERTICAL","GRASS","GRASS","GRASS","GRASS"]},{"items":["NO_SPRITE","NO_SPRITE","NO_SPRITE","NO_SPRITE","NO_SPRITE","NO_SPRITE","NO_SPRITE","NO_SPRITE","NO_SPRITE","NO_SPRITE","NO_SPRITE","NO_SPRITE","GRASS","DIRT_ROAD_CORRIDOR_VERTICAL","DARK_PATH_CORRIDOR_VERTICAL","GRASS","GRASS","GRASS","GRASS","GRASS","GRASS","GRASS","GRASS","GRASS","GRASS","GRASS","GRASS","GRASS","GRASS","GRASS","GRASS","GRASS","GRASS","GRASS","GRASS","GRASS","GRASS","DIRT_ROAD_CORRIDOR_VERTICAL","DARK_PATH_CORRIDOR_VERTICAL","GRASS","GRASS","GRASS","GRASS"]},{"items":["NO_SPRITE","NO_SPRITE","NO_SPRITE","NO_SPRITE","NO_SPRITE","NO_SPRITE","NO_SPRITE","NO_SPRITE","NO_SPRITE","NO_SPRITE","NO_SPRITE","NO_SPRITE","GRASS","DIRT_ROAD_CORRIDOR_VERTICAL","DARK_PATH_CORRIDOR_VERTICAL","GRASS","GRASS","GRASS","GRASS","GRASS","GRASS","GRASS","GRASS","GRASS","GRASS","GRASS","GRASS","GRASS","GRASS","GRASS","GRASS","GRASS","GRASS","GRASS","GRASS","GRASS","GRASS","DIRT_ROAD_CORRIDOR_VERTICAL","DARK_PATH_CORRIDOR_VERTICAL","GRASS","GRASS","GRASS","GRASS"]},{"items":["NO_SPRITE","NO_SPRITE","NO_SPRITE","NO_SPRITE","NO_SPRITE","NO_SPRITE","NO_SPRITE","NO_SPRITE","NO_SPRITE","NO_SPRITE","NO_SPRITE","NO_SPRITE","GRASS","DIRT_ROAD_CORRIDOR_VERTICAL","DARK_PATH_CORRIDOR_VERTICAL","GRASS","GRASS","GRASS","GRASS","GRASS","GRASS","GRASS","GRASS","GRASS","GRASS","GRASS","GRASS","GRASS","GRASS","GRASS","GRASS","GRASS","GRASS","GRASS","GRASS","GRASS","GRASS","DIRT_ROAD_CORRIDOR_VERTICAL","DARK_PATH_CORRIDOR_VERTICAL","GRASS","GRASS","GRASS","GRASS"]},{"items":["NO_SPRITE","NO_SPRITE","NO_SPRITE","NO_SPRITE","NO_SPRITE","NO_SPRITE","NO_SPRITE","NO_SPRITE","NO_SPRITE","NO_SPRITE","NO_SPRITE","NO_SPRITE","GRASS","DIRT_ROAD_CORRIDOR_VERTICAL","DARK_PATH_CORRIDOR_VERTICAL","GRASS","GRASS","GRASS","GRASS","GRASS","GRASS","GRASS","GRASS","GRASS","GRASS","GRASS","GRASS","GRASS","GRASS","GRASS","GRASS","GRASS","GRASS","GRASS","GRASS","GRASS","GRASS","DIRT_ROAD_CORRIDOR_VERTICAL","DARK_PATH_CORRIDOR_VERTICAL","GRASS","GRASS","GRASS","GRASS"]},{"items":["NO_SPRITE","NO_SPRITE","NO_SPRITE","NO_SPRITE","NO_SPRITE","NO_SPRITE","NO_SPRITE","NO_SPRITE","NO_SPRITE","NO_SPRITE","NO_SPRITE","NO_SPRITE","GRASS","DIRT_ROAD_CORRIDOR_VERTICAL","DARK_PATH_CORRIDOR_VERTICAL","GRASS","GRASS","GRASS","GRASS","GRASS","GRASS","GRASS","GRASS","GRASS","GRASS","GRASS","GRASS","GRASS","GRASS","GRASS","GRASS","GRASS","GRASS","GRASS","GRASS","GRASS","GRASS","DIRT_ROAD_CORRIDOR_VERTICAL","DARK_PATH_CORRIDOR_VERTICAL","GRASS","GRASS","GRASS","GRASS"]},{"items":["NO_SPRITE","NO_SPRITE","NO_SPRITE","NO_SPRITE","NO_SPRITE","NO_SPRITE","NO_SPRITE","NO_SPRITE","NO_SPRITE","NO_SPRITE","NO_SPRITE","NO_SPRITE","GRASS","GRASS","GRASS","GRASS","GRASS","GRASS","GRASS","GRASS","GRASS","GRASS","GRASS","GRASS","GRASS","GRASS","GRASS","GRASS","GRASS","GRASS","GRASS","GRASS","GRASS","GRASS","GRASS","GRASS","GRASS","DIRT_ROAD_INNER_TOP_LEFT_CORNER","DIRT_ROAD_INNER_TOP_RIGHT_CORNER","GRASS","GRASS","GRASS","GRASS"]},{"items":["NO_SPRITE","NO_SPRITE","NO_SPRITE","NO_SPRITE","NO_SPRITE","NO_SPRITE","NO_SPRITE","NO_SPRITE","NO_SPRITE","NO_SPRITE","NO_SPRITE","NO_SPRITE","DIRT_ROAD_INNER_TOP_LEFT_CORNER","DIRT_ROAD_INNER_TOP_RIGHT_CORNER","DIRT_ROAD_INNER_TOP_LEFT_CORNER","DIRT_ROAD_INNER_TOP_RIGHT_CORNER","GRASS","GRASS","GRASS","GRASS","GRASS","GRASS","GRASS","GRASS","DIRT_ROAD_INNER_TOP_LEFT_CORNER","DIRT_ROAD_INNER_TOP_RIGHT_CORNER","DIRT_ROAD_INNER_TOP_LEFT_CORNER","DIRT_ROAD_INNER_TOP_RIGHT_CORNER","GRASS","GRASS","GRASS","GRASS","GRASS","GRASS","GRASS","GRASS","GRASS","DIRT_ROAD_INNER_BOTTOM_LEFT_CORNER","DIRT_ROAD_INNER_BOTTOM_RIGHT_CORNER","GRASS","DIRT_ROAD_CORRIDOR_HORIZONTAL","DIRT_ROAD_CORRIDOR_HORIZONTAL","DIRT_ROAD_CORRIDOR_HORIZONTAL","DIRT_ROAD_CORRIDOR_HORIZONTAL","DIRT_ROAD_CORRIDOR_HORIZONTAL","DIRT_ROAD_CORRIDOR_HORIZONTAL","DIRT_ROAD_CORRIDOR_HORIZONTAL","DIRT_ROAD_CORRIDOR_HORIZONTAL"]},{"items":["NO_SPRITE","NO_SPRITE","NO_SPRITE","NO_SPRITE","NO_SPRITE","NO_SPRITE","NO_SPRITE","NO_SPRITE","NO_SPRITE","NO_SPRITE","NO_SPRITE","NO_SPRITE","DIRT_ROAD_INNER_BOTTOM_LEFT_CORNER","DIRT_ROAD_INNER_BOTTOM_RIGHT_CORNER","DIRT_ROAD_INNER_BOTTOM_LEFT_CORNER","DIRT_ROAD_INNER_BOTTOM_RIGHT_CORNER","DARK_PATH_CORRIDOR_HORIZONTAL","DARK_PATH_CORRIDOR_HORIZONTAL","DARK_PATH_CORRIDOR_HORIZONTAL","DARK_PATH_CORRIDOR_HORIZONTAL","DARK_PATH_CORRIDOR_HORIZONTAL","DARK_PATH_CORRIDOR_HORIZONTAL","DARK_PATH_CORRIDOR_HORIZONTAL","DARK_PATH_CORRIDOR_HORIZONTAL","DIRT_ROAD_INNER_BOTTOM_LEFT_CORNER","DIRT_ROAD_INNER_BOTTOM_RIGHT_CORNER","DIRT_ROAD_INNER_BOTTOM_LEFT_CORNER","DIRT_ROAD_INNER_BOTTOM_RIGHT_CORNER","DARK_PATH_CORRIDOR_HORIZONTAL","DARK_PATH_CORRIDOR_HORIZONTAL","DARK_PATH_CORRIDOR_HORIZONTAL","DARK_PATH_CORRIDOR_HORIZONTAL","DARK_PATH_CORRIDOR_HORIZONTAL","DARK_PATH_CORRIDOR_HORIZONTAL","DARK_PATH_CORRIDOR_HORIZONTAL","DARK_PATH_CORRIDOR_HORIZONTAL","DIRT_ROAD_INNER_TOP_LEFT_CORNER","DIRT_ROAD_INNER_TOP_RIGHT_CORNER","DIRT_ROAD_INNER_TOP_LEFT_CORNER","DIRT_ROAD_INNER_TOP_RIGHT_CORNER","DARK_PATH_CORRIDOR_HORIZONTAL","DARK_PATH_CORRIDOR_HORIZONTAL","DARK_PATH_CORRIDOR_HORIZONTAL","DARK_PATH_CORRIDOR_HORIZONTAL","DARK_PATH_CORRIDOR_HORIZONTAL","DARK_PATH_CORRIDOR_HORIZONTAL","DARK_PATH_CORRIDOR_HORIZONTAL","DARK_PATH_CORRIDOR_HORIZONTAL"]},{"items":["NO_SPRITE","NO_SPRITE","NO_SPRITE","NO_SPRITE","NO_SPRITE","NO_SPRITE","NO_SPRITE","NO_SPRITE","NO_SPRITE","NO_SPRITE","NO_SPRITE","NO_SPRITE","GRASS","GRASS","GRASS","GRASS","DARK_PATH_TOP_RIGHT_BOTTOM_LEFT_CORNERS","DARK_PATH_INNER_TOP_RIGHT_CORNER","GRASS","GRASS","GRASS","GRASS","GRASS","GRASS","GRASS","GRASS","GRASS","GRASS","GRASS","GRASS","GRASS","GRASS","GRASS","GRASS","GRASS","DIRT_ROAD_INNER_CORRIDOR_TOP_LEFT","DIRT_ROAD_INNER_BOTTOM_LEFT_CORNER","DIRT_ROAD_INNER_BOTTOM_RIGHT_CORNER","DIRT_ROAD_INNER_BOTTOM_LEFT_CORNER","DIRT_ROAD_INNER_BOTTOM_RIGHT_CORNER","GRASS","GRASS","GRASS"]},{"items":["NO_SPRITE","NO_SPRITE","NO_SPRITE","NO_SPRITE","NO_SPRITE","NO_SPRITE","NO_SPRITE","NO_SPRITE","NO_SPRITE","NO_SPRITE","NO_SPRITE","NO_SPRITE","GRASS","DIRT_ROAD_CORRIDOR_VERTICAL","DARK_PATH_CORRIDOR_VERTICAL","DIRT_ROAD_INNER_CORRIDOR_TOP_RIGHT","DARK_PATH_INNER_BOTTOM_LEFT_CORNER","DARK_PATH_TOP_RIGHT_BOTTOM_LEFT_CORNERS","DARK_PATH_INNER_TOP_RIGHT_CORNER","GRASS","GRASS","GRASS","GRASS","GRASS","GRASS","GRASS","GRASS","GRASS","GRASS","GRASS","GRASS","GRASS","GRASS","GRASS","DIRT_ROAD_INNER_CORRIDOR_TOP_LEFT","DIRT_ROAD_INNER_BOTTOM_RIGHT_CORNER","DARK_PATH_INNER_TOP_LEFT_CORNER","DARK_PATH_TOP_LEFT_BOTTOM_RIGHT_CORNER","DARK_PATH_INNER_BOTTOM_RIGHT_CORNER","NO_SPRITE","NO_SPRITE","NO_SPRITE","GRASS"]},{"items":["NO_SPRITE","NO_SPRITE","NO_SPRITE","NO_SPRITE","NO_SPRITE","NO_SPRITE","NO_SPRITE","NO_SPRITE","NO_SPRITE","NO_SPRITE","NO_SPRITE","NO_SPRITE","GRASS","DIRT_ROAD_CORRIDOR_VERTICAL","DARK_PATH_CORRIDOR_VERTICAL","DIRT_ROAD_INNER_CORRIDOR_BOTTOM_LEFT","DIRT_ROAD_INNER_CORRIDOR_TOP_RIGHT","DARK_PATH_INNER_BOTTOM_LEFT_CORNER","DARK_PATH_TOP_RIGHT_BOTTOM_LEFT_CORNERS","DARK_PATH_INNER_TOP_RIGHT_CORNER","GRASS","GRASS","GRASS","GRASS","GRASS","GRASS","GRASS","GRASS","GRASS","GRASS","GRASS","GRASS","GRASS","DIRT_ROAD_INNER_CORRIDOR_TOP_LEFT","DIRT_ROAD_INNER_BOTTOM_RIGHT_CORNER","DARK_PATH_INNER_TOP_LEFT_CORNER","DARK_PATH_TOP_LEFT_BOTTOM_RIGHT_CORNER","DARK_PATH_INNER_BOTTOM_RIGHT_CORNER"]},{"items":["NO_SPRITE","NO_SPRITE","NO_SPRITE","NO_SPRITE","NO_SPRITE","NO_SPRITE","NO_SPRITE","NO_SPRITE","NO_SPRITE","NO_SPRITE","NO_SPRITE","NO_SPRITE","GRASS","DIRT_ROAD_CORRIDOR_VERTICAL","DARK_PATH_CORRIDOR_VERTICAL","GRASS","DIRT_ROAD_INNER_CORRIDOR_BOTTOM_LEFT","DIRT_ROAD_INNER_CORRIDOR_TOP_RIGHT","DARK_PATH_INNER_BOTTOM_LEFT_CORNER","DARK_PATH_TOP_RIGHT_BOTTOM_LEFT_CORNERS","DARK_PATH_INNER_TOP_RIGHT_CORNER","GRASS","GRASS","GRASS","GRASS","GRASS","GRASS","GRASS","GRASS","GRASS","GRASS","GRASS","DIRT_ROAD_INNER_CORRIDOR_TOP_LEFT","DIRT_ROAD_INNER_BOTTOM_RIGHT_CORNER","DARK_PATH_INNER_TOP_LEFT_CORNER","DARK_PATH_TOP_LEFT_BOTTOM_RIGHT_CORNER","DARK_PATH_INNER_BOTTOM_RIGHT_CORNER"]},{"items":["NO_SPRITE","NO_SPRITE","NO_SPRITE","NO_SPRITE","NO_SPRITE","NO_SPRITE","NO_SPRITE","NO_SPRITE","NO_SPRITE","NO_SPRITE","NO_SPRITE","NO_SPRITE","GRASS","DIRT_ROAD_CORRIDOR_VERTICAL","DARK_PATH_CORRIDOR_VERTICAL","GRASS","GRASS","DIRT_ROAD_INNER_CORRIDOR_BOTTOM_LEFT","DIRT_ROAD_INNER_CORRIDOR_TOP_RIGHT","DARK_PATH_INNER_BOTTOM_LEFT_CORNER","DARK_PATH_TOP_RIGHT_BOTTOM_LEFT_CORNERS","DARK_PATH_INNER_TOP_RIGHT_CORNER","GRASS","GRASS","GRASS","GRASS","GRASS","GRASS","GRASS","GRASS","GRASS","DIRT_ROAD_INNER_CORRIDOR_TOP_LEFT","DIRT_ROAD_INNER_BOTTOM_RIGHT_CORNER","DARK_PATH_INNER_TOP_LEFT_CORNER","DARK_PATH_TOP_LEFT_BOTTOM_RIGHT_CORNER","DARK_PATH_INNER_BOTTOM_RIGHT_CORNER"]},{"items":["NO_SPRITE","NO_SPRITE","NO_SPRITE","NO_SPRITE","NO_SPRITE","NO_SPRITE","NO_SPRITE","NO_SPRITE","NO_SPRITE","NO_SPRITE","NO_SPRITE","NO_SPRITE","GRASS","DIRT_ROAD_CORRIDOR_VERTICAL","DARK_PATH_CORRIDOR_VERTICAL","GRASS","GRASS","GRASS","DIRT_ROAD_INNER_CORRIDOR_BOTTOM_LEFT","DIRT_ROAD_INNER_CORRIDOR_TOP_RIGHT","DARK_PATH_INNER_BOTTOM_LEFT_CORNER","DARK_PATH_TOP_RIGHT_BOTTOM_LEFT_CORNERS","DARK_PATH_INNER_TOP_RIGHT_CORNER","GRASS","GRASS","GRASS","GRASS","GRASS","GRASS","GRASS","DIRT_ROAD_INNER_CORRIDOR_TOP_LEFT","DIRT_ROAD_INNER_BOTTOM_RIGHT_CORNER","DARK_PATH_INNER_TOP_LEFT_CORNER","DARK_PATH_TOP_LEFT_BOTTOM_RIGHT_CORNER","DARK_PATH_INNER_BOTTOM_RIGHT_CORNER"]},{"items":["NO_SPRITE","NO_SPRITE","NO_SPRITE","NO_SPRITE","NO_SPRITE","NO_SPRITE","NO_SPRITE","NO_SPRITE","NO_SPRITE","NO_SPRITE","NO_SPRITE","NO_SPRITE","GRASS","DIRT_ROAD_CORRIDOR_VERTICAL","DARK_PATH_CORRIDOR_VERTICAL","GRASS","GRASS","GRASS","GRASS","DIRT_ROAD_INNER_CORRIDOR_BOTTOM_LEFT","DIRT_ROAD_INNER_CORRIDOR_TOP_RIGHT","DARK_PATH_INNER_BOTTOM_LEFT_CORNER","DARK_PATH_TOP_RIGHT_BOTTOM_LEFT_CORNERS","DARK_PATH_INNER_TOP_RIGHT_CORNER","GRASS","GRASS","GRASS","GRASS","GRASS","DIRT_ROAD_INNER_CORRIDOR_TOP_LEFT","DIRT_ROAD_INNER_BOTTOM_RIGHT_CORNER","DARK_PATH_INNER_TOP_LEFT_CORNER","DARK_PATH_TOP_LEFT_BOTTOM_RIGHT_CORNER","DARK_PATH_INNER_BOTTOM_RIGHT_CORNER"]},{"items":["NO_SPRITE","NO_SPRITE","NO_SPRITE","NO_SPRITE","NO_SPRITE","NO_SPRITE","NO_SPRITE","NO_SPRITE","NO_SPRITE","NO_SPRITE","NO_SPRITE","NO_SPRITE","GRASS","DIRT_ROAD_CORRIDOR_VERTICAL","DARK_PATH_CORRIDOR_VERTICAL","GRASS","GRASS","GRASS","GRASS","GRASS","DIRT_ROAD_INNER_CORRIDOR_BOTTOM_LEFT","DIRT_ROAD_INNER_CORRIDOR_TOP_RIGHT","DARK_PATH_INNER_BOTTOM_LEFT_CORNER","DARK_PATH_TOP_RIGHT_BOTTOM_LEFT_CORNERS","DARK_PATH_INNER_TOP_RIGHT_CORNER","GRASS","GRASS","GRASS","DIRT_ROAD_INNER_CORRIDOR_TOP_LEFT","DIRT_ROAD_INNER_BOTTOM_RIGHT_CORNER","DARK_PATH_INNER_TOP_LEFT_CORNER","DARK_PATH_TOP_LEFT_BOTTOM_RIGHT_CORNER","DARK_PATH_INNER_BOTTOM_RIGHT_CORNER"]},{"items":["NO_SPRITE","NO_SPRITE","NO_SPRITE","NO_SPRITE","NO_SPRITE","NO_SPRITE","NO_SPRITE","NO_SPRITE","NO_SPRITE","NO_SPRITE","NO_SPRITE","NO_SPRITE","GRASS","DIRT_ROAD_CORRIDOR_VERTICAL","DARK_PATH_CORRIDOR_VERTICAL","GRASS","GRASS","GRASS","GRASS","GRASS","GRASS","DIRT_ROAD_INNER_CORRIDOR_BOTTOM_LEFT","DIRT_ROAD_INNER_CORRIDOR_TOP_RIGHT","DARK_PATH_INNER_BOTTOM_LEFT_CORNER","DARK_PATH_TOP_RIGHT_BOTTOM_LEFT_CORNERS","DARK_PATH_INNER_TOP_RIGHT_CORNER","GRASS","DIRT_ROAD_INNER_CORRIDOR_TOP_LEFT","DIRT_ROAD_INNER_BOTTOM_RIGHT_CORNER","DARK_PATH_INNER_TOP_LEFT_CORNER","DARK_PATH_TOP_LEFT_BOTTOM_RIGHT_CORNER","DARK_PATH_INNER_BOTTOM_RIGHT_CORNER"]},{"items":["NO_SPRITE","NO_SPRITE","NO_SPRITE","NO_SPRITE","NO_SPRITE","NO_SPRITE","NO_SPRITE","NO_SPRITE","NO_SPRITE","NO_SPRITE","NO_SPRITE","NO_SPRITE","GRASS","GRASS","GRASS","GRASS","GRASS","GRASS","GRASS","GRASS","GRASS","GRASS","DIRT_ROAD_INNER_CORRIDOR_BOTTOM_LEFT","DIRT_ROAD_INNER_CORRIDOR_TOP_RIGHT","GRASS","GRASS","GRASS","GRASS","DARK_PATH_INNER_TOP_LEFT_CORNER","DARK_PATH_TOP_LEFT_BOTTOM_RIGHT_CORNER","DARK_PATH_INNER_BOTTOM_RIGHT_CORNER"]},{"items":["NO_SPRITE","NO_SPRITE","NO_SPRITE","NO_SPRITE","NO_SPRITE","NO_SPRITE","NO_SPRITE","NO_SPRITE","NO_SPRITE","NO_SPRITE","NO_SPRITE","NO_SPRITE","DIRT_ROAD_INNER_TOP_LEFT_CORNER","DIRT_ROAD_INNER_TOP_RIGHT_CORNER","DIRT_ROAD_INNER_TOP_LEFT_CORNER","DIRT_ROAD_INNER_TOP_RIGHT_CORNER","GRASS","GRASS","GRASS","GRASS","GRASS","GRASS","GRASS","DIRT_ROAD_INNER_CORRIDOR_BOTTOM_LEFT","DIRT_ROAD_INNER_TOP_LEFT_CORNER","DIRT_ROAD_INNER_TOP_RIGHT_CORNER","DIRT_ROAD_INNER_TOP_LEFT_CORNER","DIRT_ROAD_INNER_TOP_RIGHT_CORNER","DARK_PATH_TOP_LEFT_BOTTOM_RIGHT_CORNER","DARK_PATH_INNER_BOTTOM_RIGHT_CORNER"]},{"items":["NO_SPRITE","NO_SPRITE","NO_SPRITE","NO_SPRITE","NO_SPRITE","NO_SPRITE","NO_SPRITE","NO_SPRITE","NO_SPRITE","NO_SPRITE","NO_SPRITE","NO_SPRITE","DIRT_ROAD_INNER_BOTTOM_LEFT_CORNER","DIRT_ROAD_INNER_BOTTOM_RIGHT_CORNER","DIRT_ROAD_INNER_BOTTOM_LEFT_CORNER","DIRT_ROAD_INNER_BOTTOM_RIGHT_CORNER","GRASS","GRASS","GRASS","GRASS","GRASS","GRASS","GRASS","GRASS","DIRT_ROAD_INNER_BOTTOM_LEFT_CORNER","DIRT_ROAD_INNER_BOTTOM_RIGHT_CORNER","DIRT_ROAD_INNER_BOTTOM_LEFT_CORNER","DIRT_ROAD_INNER_BOTTOM_RIGHT_CORNER","DARK_PATH_TOP_RIGHT_BOTTOM_LEFT_CORNERS","DARK_PATH_INNER_TOP_RIGHT_CORNER"]},{"items":["NO_SPRITE","NO_SPRITE","NO_SPRITE","NO_SPRITE","NO_SPRITE","NO_SPRITE","NO_SPRITE","NO_SPRITE","NO_SPRITE","NO_SPRITE","NO_SPRITE","NO_SPRITE","GRASS","GRASS","GRASS","GRASS","GRASS","GRASS","GRASS","GRASS","GRASS","GRASS","GRASS","GRASS","GRASS","GRASS","GRASS","GRASS","DARK_PATH_INNER_BOTTOM_LEFT_CORNER","DARK_PATH_TOP_RIGHT_BOTTOM_LEFT_CORNERS","DARK_PATH_INNER_TOP_RIGHT_CORNER"]},{"items":["NO_SPRITE","NO_SPRITE","NO_SPRITE","NO_SPRITE","NO_SPRITE","NO_SPRITE","NO_SPRITE","NO_SPRITE","NO_SPRITE","NO_SPRITE","NO_SPRITE","NO_SPRITE","GRASS","DIRT_ROAD_CORRIDOR_VERTICAL","DARK_PATH_CORRIDOR_VERTICAL","GRASS","GRASS","GRASS","GRASS","GRASS","GRASS","GRASS","GRASS","DARK_PATH_INNER_TOP_LEFT_CORNER","DARK_PATH_TOP_LEFT_BOTTOM_RIGHT_CORNER","DARK_PATH_INNER_BOTTOM_RIGHT_CORNER","GRASS","NO_SPRITE","NO_SPRITE","DARK_PATH_INNER_BOTTOM_LEFT_CORNER","DARK_PATH_TOP_RIGHT_BOTTOM_LEFT_CORNERS","DARK_PATH_INNER_TOP_RIGHT_CORNER"]},{"items":["NO_SPRITE","NO_SPRITE","NO_SPRITE","NO_SPRITE","NO_SPRITE","NO_SPRITE","NO_SPRITE","NO_SPRITE","NO_SPRITE","NO_SPRITE","NO_SPRITE","NO_SPRITE","GRASS","DIRT_ROAD_CORRIDOR_VERTICAL","DARK_PATH_CORRIDOR_VERTICAL","GRASS","GRASS","GRASS","GRASS","GRASS","GRASS","GRASS","DARK_PATH_INNER_TOP_LEFT_CORNER","DARK_PATH_TOP_LEFT_BOTTOM_RIGHT_CORNER","DARK_PATH_INNER_BOTTOM_RIGHT_CORNER","GRASS","NO_SPRITE","NO_SPRITE","NO_SPRITE","NO_SPRITE","DARK_PATH_INNER_BOTTOM_LEFT_CORNER","DARK_PATH_TOP_RIGHT_BOTTOM_LEFT_CORNERS","DARK_PATH_INNER_TOP_RIGHT_CORNER"]},{"items":["NO_SPRITE","NO_SPRITE","NO_SPRITE","NO_SPRITE","NO_SPRITE","NO_SPRITE","NO_SPRITE","NO_SPRITE","NO_SPRITE","NO_SPRITE","NO_SPRITE","NO_SPRITE","GRASS","DIRT_ROAD_CORRIDOR_VERTICAL","DARK_PATH_CORRIDOR_VERTICAL","GRASS","GRASS","GRASS","GRASS","GRASS","GRASS","DARK_PATH_INNER_TOP_LEFT_CORNER","DARK_PATH_TOP_LEFT_BOTTOM_RIGHT_CORNER","DARK_PATH_INNER_BOTTOM_RIGHT_CORNER","GRASS","NO_SPRITE","NO_SPRITE","NO_SPRITE","NO_SPRITE","NO_SPRITE","NO_SPRITE","DARK_PATH_INNER_BOTTOM_LEFT_CORNER","DARK_PATH_TOP_RIGHT_BOTTOM_LEFT_CORNERS","DARK_PATH_INNER_TOP_RIGHT_CORNER"]},{"items":["NO_SPRITE","NO_SPRITE","NO_SPRITE","NO_SPRITE","NO_SPRITE","NO_SPRITE","NO_SPRITE","NO_SPRITE","NO_SPRITE","NO_SPRITE","NO_SPRITE","NO_SPRITE","GRASS","DIRT_ROAD_CORRIDOR_VERTICAL","DARK_PATH_CORRIDOR_VERTICAL","GRASS","GRASS","GRASS","GRASS","GRASS","DARK_PATH_INNER_TOP_LEFT_CORNER","DARK_PATH_TOP_LEFT_BOTTOM_RIGHT_CORNER","DARK_PATH_INNER_BOTTOM_RIGHT_CORNER","GRASS","NO_SPRITE","NO_SPRITE","NO_SPRITE","NO_SPRITE","NO_SPRITE","NO_SPRITE","NO_SPRITE","NO_SPRITE","DARK_PATH_INNER_BOTTOM_LEFT_CORNER","DARK_PATH_TOP_RIGHT_BOTTOM_LEFT_CORNERS","DARK_PATH_INNER_TOP_RIGHT_CORNER"]},{"items":["NO_SPRITE","NO_SPRITE","NO_SPRITE","NO_SPRITE","NO_SPRITE","NO_SPRITE","NO_SPRITE","NO_SPRITE","NO_SPRITE","NO_SPRITE","NO_SPRITE","NO_SPRITE","GRASS","DIRT_ROAD_CORRIDOR_VERTICAL","DARK_PATH_CORRIDOR_VERTICAL","GRASS","GRASS","GRASS","GRASS","DARK_PATH_INNER_TOP_LEFT_CORNER","DARK_PATH_TOP_LEFT_BOTTOM_RIGHT_CORNER","DARK_PATH_INNER_BOTTOM_RIGHT_CORNER","GRASS","NO_SPRITE","NO_SPRITE","NO_SPRITE","NO_SPRITE","NO_SPRITE","NO_SPRITE","NO_SPRITE","NO_SPRITE","NO_SPRITE","NO_SPRITE","DARK_PATH_INNER_BOTTOM_LEFT_CORNER","DARK_PATH_TOP_RIGHT_BOTTOM_LEFT_CORNERS","DARK_PATH_INNER_TOP_RIGHT_CORNER"]},{"items":["NO_SPRITE","NO_SPRITE","NO_SPRITE","NO_SPRITE","NO_SPRITE","NO_SPRITE","NO_SPRITE","NO_SPRITE","NO_SPRITE","NO_SPRITE","NO_SPRITE","NO_SPRITE","GRASS","DIRT_ROAD_CORRIDOR_VERTICAL","DARK_PATH_CORRIDOR_VERTICAL","GRASS","GRASS","GRASS","DARK_PATH_INNER_TOP_LEFT_CORNER","DARK_PATH_TOP_LEFT_BOTTOM_RIGHT_CORNER","DARK_PATH_INNER_BOTTOM_RIGHT_CORNER","GRASS","NO_SPRITE","NO_SPRITE","NO_SPRITE","NO_SPRITE","NO_SPRITE","NO_SPRITE","NO_SPRITE","NO_SPRITE","NO_SPRITE","NO_SPRITE","NO_SPRITE","NO_SPRITE","DARK_PATH_INNER_BOTTOM_LEFT_CORNER","DARK_PATH_TOP_RIGHT_BOTTOM_LEFT_CORNERS","DARK_PATH_INNER_TOP_RIGHT_CORNER"]},{"items":["NO_SPRITE","NO_SPRITE","NO_SPRITE","NO_SPRITE","NO_SPRITE","NO_SPRITE","NO_SPRITE","NO_SPRITE","NO_SPRITE","NO_SPRITE","NO_SPRITE","NO_SPRITE","GRASS","DIRT_ROAD_CORRIDOR_VERTICAL","DARK_PATH_CORRIDOR_VERTICAL","GRASS","GRASS","DARK_PATH_INNER_TOP_LEFT_CORNER","DARK_PATH_TOP_LEFT_BOTTOM_RIGHT_CORNER","DARK_PATH_INNER_BOTTOM_RIGHT_CORNER","GRASS","NO_SPRITE","NO_SPRITE","NO_SPRITE","NO_SPRITE","NO_SPRITE","NO_SPRITE","NO_SPRITE","NO_SPRITE","NO_SPRITE","NO_SPRITE","NO_SPRITE","NO_SPRITE","NO_SPRITE","NO_SPRITE","DARK_PATH_INNER_BOTTOM_LEFT_CORNER","DARK_PATH_TOP_RIGHT_BOTTOM_LEFT_CORNERS","DARK_PATH_INNER_TOP_RIGHT_CORNER"]},{"items":["NO_SPRITE","NO_SPRITE","NO_SPRITE","NO_SPRITE","NO_SPRITE","NO_SPRITE","NO_SPRITE","NO_SPRITE","NO_SPRITE","NO_SPRITE","NO_SPRITE","NO_SPRITE","GRASS","DIRT_ROAD_CORRIDOR_VERTICAL","DARK_PATH_CORRIDOR_VERTICAL","GRASS","DARK_PATH_INNER_TOP_LEFT_CORNER","DARK_PATH_TOP_LEFT_BOTTOM_RIGHT_CORNER","DARK_PATH_INNER_BOTTOM_RIGHT_CORNER","GRASS","NO_SPRITE","NO_SPRITE","NO_SPRITE","NO_SPRITE","NO_SPRITE","NO_SPRITE","NO_SPRITE","NO_SPRITE","NO_SPRITE","NO_SPRITE","NO_SPRITE","NO_SPRITE","NO_SPRITE","NO_SPRITE","NO_SPRITE","NO_SPRITE","DARK_PATH_INNER_BOTTOM_LEFT_CORNER","DARK_PATH_TOP_RIGHT_BOTTOM_LEFT_CORNERS","DARK_PATH_INNER_TOP_RIGHT_CORNER"]},{"items":["NO_SPRITE","NO_SPRITE","NO_SPRITE","NO_SPRITE","NO_SPRITE","NO_SPRITE","NO_SPRITE","NO_SPRITE","NO_SPRITE","NO_SPRITE","NO_SPRITE","NO_SPRITE","GRASS","GRASS","GRASS","GRASS","DARK_PATH_TOP_LEFT_BOTTOM_RIGHT_CORNER","DARK_PATH_INNER_BOTTOM_RIGHT_CORNER","GRASS","NO_SPRITE","NO_SPRITE","NO_SPRITE","NO_SPRITE","NO_SPRITE","NO_SPRITE","NO_SPRITE","NO_SPRITE","NO_SPRITE","NO_SPRITE","NO_SPRITE","NO_SPRITE","NO_SPRITE","NO_SPRITE","NO_SPRITE","NO_SPRITE","NO_SPRITE","GRASS","GRASS","GRASS","GRASS"]},{"items":["NO_SPRITE","DIRT_ROAD_INNER_TOP_LEFT_CORNER","DIRT_ROAD_INNER_TOP_RIGHT_CORNER","DIRT_ROAD_CORRIDOR_HORIZONTAL","DIRT_ROAD_CORRIDOR_HORIZONTAL","DIRT_ROAD_CORRIDOR_HORIZONTAL","DIRT_ROAD_CORRIDOR_HORIZONTAL","DIRT_ROAD_CORRIDOR_HORIZONTAL","DIRT_ROAD_CORRIDOR_HORIZONTAL","DIRT_ROAD_CORRIDOR_HORIZONTAL","DIRT_ROAD_CORRIDOR_HORIZONTAL","DIRT_ROAD_CORRIDOR_HORIZONTAL","DIRT_ROAD_INNER_TOP_LEFT_CORNER","DIRT_ROAD_INNER_TOP_RIGHT_CORNER","DIRT_ROAD_INNER_TOP_LEFT_CORNER","DIRT_ROAD_INNER_TOP_RIGHT_CORNER","DARK_PATH_INNER_BOTTOM_RIGHT_CORNER","NO_SPRITE","NO_SPRITE","NO_SPRITE","NO_SPRITE","NO_SPRITE","NO_SPRITE","NO_SPRITE","NO_SPRITE","NO_SPRITE","NO_SPRITE","NO_SPRITE","NO_SPRITE","NO_SPRITE","NO_SPRITE","NO_SPRITE","NO_SPRITE","NO_SPRITE","NO_SPRITE","NO_SPRITE","DIRT_ROAD_INNER_TOP_LEFT_CORNER","DIRT_ROAD_INNER_TOP_RIGHT_CORNER","DIRT_ROAD_INNER_TOP_LEFT_CORNER","DIRT_ROAD_INNER_TOP_RIGHT_CORNER"]},{"items":["NO_SPRITE","DIRT_ROAD_INNER_BOTTOM_LEFT_CORNER","DIRT_ROAD_INNER_BOTTOM_RIGHT_CORNER","DARK_PATH_CORRIDOR_HORIZONTAL","DARK_PATH_CORRIDOR_HORIZONTAL","DARK_PATH_CORRIDOR_HORIZONTAL","DARK_PATH_CORRIDOR_HORIZONTAL","DARK_PATH_CORRIDOR_HORIZONTAL","DARK_PATH_CORRIDOR_HORIZONTAL","DARK_PATH_CORRIDOR_HORIZONTAL","DARK_PATH_CORRIDOR_HORIZONTAL","DARK_PATH_CORRIDOR_HORIZONTAL","DIRT_ROAD_INNER_BOTTOM_LEFT_CORNER","DIRT_ROAD_INNER_BOTTOM_RIGHT_CORNER","DIRT_ROAD_INNER_BOTTOM_LEFT_CORNER","DIRT_ROAD_INNER_BOTTOM_RIGHT_CORNER","NO_SPRITE","NO_SPRITE","NO_SPRITE","NO_SPRITE","NO_SPRITE","NO_SPRITE","NO_SPRITE","NO_SPRITE","NO_SPRITE","NO_SPRITE","NO_SPRITE","NO_SPRITE","NO_SPRITE","NO_SPRITE","NO_SPRITE","NO_SPRITE","NO_SPRITE","NO_SPRITE","NO_SPRITE","NO_SPRITE","DIRT_ROAD_INNER_BOTTOM_LEFT_CORNER","DIRT_ROAD_INNER_BOTTOM_RIGHT_CORNER","DIRT_ROAD_INNER_BOTTOM_LEFT_CORNER","DIRT_ROAD_INNER_BOTTOM_RIGHT_CORNER"]},{"items":["NO_SPRITE","NO_SPRITE","NO_SPRITE","NO_SPRITE","NO_SPRITE","NO_SPRITE","NO_SPRITE","NO_SPRITE","NO_SPRITE","NO_SPRITE","NO_SPRITE","NO_SPRITE","GRASS","GRASS","GRASS","GRASS","NO_SPRITE","NO_SPRITE","NO_SPRITE","NO_SPRITE","NO_SPRITE","NO_SPRITE","NO_SPRITE","NO_SPRITE","NO_SPRITE","NO_SPRITE","NO_SPRITE","NO_SPRITE","NO_SPRITE","NO_SPRITE","NO_SPRITE","NO_SPRITE","NO_SPRITE","NO_SPRITE","NO_SPRITE","NO_SPRITE","GRASS","GRASS","GRASS","GRASS"]}]}]}