{
  "sheets": [
    {
      "resource": "game/PINBALL/png/Basic.png",
      "ppm": 32,
      "sprites": [
        {},
        {
          "type": "SPRITE_BASIC_BALL",
          "regular": {
            "rect": {
              "w": 16,
              "h": 16
            },
            "fixtures": [
              {
                "circle": {
                  "spriteOriginToFixtureCenterVecPx": {},
                  "radiusPx": 8
                }
              }
            ]
          }
        },
        {
          "type": "SPRITE_BASIC_FLIPPER_LEFT",
          "regular": {
            "rect": {
              "x": 32,
              "w": 64,
              "h": 32
            },
            "centerToOriginVecPx": {
              "x": -23.5
            },
            "fixtures": [
              {
                "circle": {
                  "spriteOriginToFixtureCenterVecPx": {
                    "x": 1.5
                  },
                  "radiusPx": 8
                }
              },
              {
                "circle": {
                  "spriteOriginToFixtureCenterVecPx": {
                    "x": 50.5
                  },
                  "radiusPx": 5
                }
              },
              {
                "chain": {
                  "points": [
                    {
                      "x": 50.5,
                      "y": 5
                    },
                    {
                      "x": 1.5,
                      "y": 9
                    },
                    {
                      "x": 1.5,
                      "y": -9
                    },
                    {
                      "x": 50.5,
                      "y": -5
                    }
                  ]
                }
              }
            ]
          }
        },
        {
          "type": "SPRITE_BASIC_FLIPPER_RIGHT",
          "regular": {
            "rect": {
              "x": 32,
              "w": 64,
              "h": 32
            },
            "centerToOriginVecPx": {
              "x": -23.5
            },
            "fixtures": [
              {
                "circle": {
                  "spriteOriginToFixtureCenterVecPx": {
                    "x": 1.5
                  },
                  "radiusPx": 8
                }
              },
              {
                "circle": {
                  "spriteOriginToFixtureCenterVecPx": {
                    "x": 50.5
                  },
                  "radiusPx": 5
                }
              },
              {
                "chain": {
                  "points": [
                    {
                      "x": 50.5,
                      "y": 5
                    },
                    {
                      "x": 1.5,
                      "y": 9
                    },
                    {
                      "x": 1.5,
                      "y": -9
                    },
                    {
                      "x": 50.5,
                      "y": -5
                    }
                  ]
                }
              }
            ]
          }
        },
        {
          "type": "SPRITE_BASIC_WALL_2X1",
          "regular": {
            "rect": {
              "x": 96,
              "y": 8,
              "w": 64,
              "h": 16
            },
            "fixtures": [
              {
                "rectangle": {
                  "dimsPx": {
                    "w": 64,
                    "h": 16
                  }
                }
              }
            ]
          }
        }
      ]
    }
  ]
}